cli.py
crawler/__init__.py
crawler/crawler.py
crawler/config/__init__.py
crawler/config/settings.py
fuck/__init__.py
fuck/cli.py
fuck/manage.py
fuck_spoiler-1.1.1.dist-info/METADATA
fuck_spoiler-1.1.1.dist-info/RECORD
fuck_spoiler-1.1.1.dist-info/WHEEL
fuck_spoiler-1.1.1.dist-info/entry_points.txt
fuck_spoiler-1.1.1.dist-info/top_level.txt
utils/__init__.py
utils/rules.py
