Metadata-Version: 2.1
Name: fuck-spoiler
Version: 1.1.1
Summary: An anti spoiler wechat robot.
Home-page: https://github.com/hj24/fuck-spoiler
Author: hj24
Author-email: mambahj24@gmail.com
License: MIT
Platform: UNKNOWN
Classifier: License :: OSI Approved :: MIT License
Classifier: Programming Language :: Python
Classifier: Programming Language :: Python :: 3
Classifier: Programming Language :: Python :: 3.6
Classifier: Programming Language :: Python :: Implementation :: CPython
Classifier: Programming Language :: Python :: Implementation :: PyPy
Requires-Python: >=3
Requires-Dist: requests
Requires-Dist: beautifulsoup4
Requires-Dist: itchat
Requires-Dist: jieba
